<?xml version="1.0" encoding="UTF-8"?>
<!DOCTYPE why3session PUBLIC "-//Why3//proof session v5//EN"
"http://why3.lri.fr/why3session.dtd">
<why3session shape_version="6">
<prover id="0" name="altergo" version="1.30-gnatprove" timelimit="0" steplimit="0" memlimit="0"/>
<prover id="1" name="CVC5" version="0.0.7-gnatprove" timelimit="0" steplimit="0" memlimit="0"/>
<prover id="2" name="Z3" version="4.5.1-gnatprove" timelimit="1" steplimit="0" memlimit="1000"/>
<prover id="3" name="Trivial" version="1.0" alternative="trivial" timelimit="1" steplimit="1" memlimit="1000"/>
<file format="gnat-json" proved="true">
<path name=".."/><path name=".."/><path name=".."/><path name=".."/><path name=".."/>
<path name=".."/><path name=".."/><path name=".."/><path name=".."/><path name=".."/>
<path name="tmp"/><path name="tmpux6py1be"/><path name="automation_request_validator"/>
<path name="gnatprove"/><path name="19227e4922691706f6a2-g_region_and_keepin_keepout_zones.gnat-json"/>
<theory name="Automation_request_validator__check_required_operating_region_and_keepin_keepout_zones__subprogram_def" proved="true">
 <goal name="def&#39;vc" proved="true">
 <transf name="split_goal_wp_conj" proved="true" >
  <goal name="def&#39;vc.0" proved="true">
  <proof prover="3"><result status="valid" steps="1"/></proof>
  </goal>
  <goal name="def&#39;vc.1" proved="true">
  <proof prover="0" steplimit="12" obsolete="true"><result status="steplimitexceeded" steps="13"/></proof>
  <proof prover="1" steplimit="1002"><result status="valid" steps="910"/></proof>
  <proof prover="2" obsolete="true"><result status="valid" steps="649"/></proof>
  </goal>
  <goal name="def&#39;vc.2" proved="true">
  <proof prover="3"><result status="valid" steps="1"/></proof>
  </goal>
  <goal name="def&#39;vc.3" proved="true">
  <proof prover="0" steplimit="18" obsolete="true"><result status="steplimitexceeded" steps="19"/></proof>
  <proof prover="1" steplimit="1377"><result status="valid" steps="1251"/></proof>
  <proof prover="2" obsolete="true"><result status="valid" steps="921"/></proof>
  </goal>
  <goal name="def&#39;vc.4" proved="true">
  <proof prover="0" steplimit="52" obsolete="true"><result status="steplimitexceeded" steps="53"/></proof>
  <proof prover="1" steplimit="2268"><result status="valid" steps="2061"/></proof>
  <proof prover="2" obsolete="true"><result status="valid" steps="2016"/></proof>
  </goal>
  <goal name="def&#39;vc.5" proved="true">
  <proof prover="3"><result status="valid" steps="1"/></proof>
  </goal>
  <goal name="def&#39;vc.6" proved="true">
  <proof prover="0" steplimit="86" obsolete="true"><result status="steplimitexceeded" steps="87"/></proof>
  <proof prover="1" steplimit="4167"><result status="valid" steps="3788"/></proof>
  <proof prover="2" obsolete="true"><result status="valid" steps="15088"/></proof>
  </goal>
  <goal name="def&#39;vc.7" proved="true">
  <proof prover="0" steplimit="120" obsolete="true"><result status="steplimitexceeded" steps="134"/></proof>
  <proof prover="1" steplimit="4630"><result status="valid" steps="4209"/></proof>
  <proof prover="2" obsolete="true"><result status="valid" steps="15484"/></proof>
  </goal>
  <goal name="def&#39;vc.8" proved="true">
  <proof prover="0" steplimit="101" obsolete="true"><result status="steplimitexceeded" steps="105"/></proof>
  <proof prover="1" steplimit="5519"><result status="valid" steps="5017"/></proof>
  <proof prover="2" obsolete="true"><result status="valid" steps="19382"/></proof>
  </goal>
  <goal name="def&#39;vc.9" proved="true">
  <proof prover="0" steplimit="223" obsolete="true"><result status="steplimitexceeded" steps="163"/></proof>
  <proof prover="1" steplimit="6225"><result status="valid" steps="5659"/></proof>
  <proof prover="2" obsolete="true"><result status="valid" steps="19788"/></proof>
  </goal>
  <goal name="def&#39;vc.10" proved="true">
  <proof prover="3"><result status="valid" steps="1"/></proof>
  </goal>
  <goal name="def&#39;vc.11" proved="true">
  <proof prover="0" steplimit="210" obsolete="true"><result status="steplimitexceeded" steps="214"/></proof>
  <proof prover="1" steplimit="4097"><result status="valid" steps="3724"/></proof>
  <proof prover="2" obsolete="true"><result status="valid" steps="3463"/></proof>
  </goal>
  <goal name="def&#39;vc.12" proved="true">
  <proof prover="0" steplimit="236" obsolete="true"><result status="steplimitexceeded" steps="219"/></proof>
  <proof prover="1" steplimit="6814"><result status="valid" steps="6194"/></proof>
  <proof prover="2" obsolete="true"><result status="valid" steps="10777"/></proof>
  </goal>
  <goal name="def&#39;vc.13" proved="true">
  <proof prover="3"><result status="valid" steps="1"/></proof>
  </goal>
  <goal name="def&#39;vc.14" proved="true">
  <proof prover="3"><result status="valid" steps="1"/></proof>
  </goal>
  <goal name="def&#39;vc.15" proved="true">
  <proof prover="0" steplimit="43" obsolete="true"><result status="steplimitexceeded" steps="44"/></proof>
  <proof prover="1" steplimit="4473"><result status="valid" steps="4066"/></proof>
  <proof prover="2" obsolete="true"><result status="valid" steps="5203"/></proof>
  </goal>
  <goal name="def&#39;vc.16" proved="true">
  <proof prover="0" steplimit="57" obsolete="true"><result status="steplimitexceeded" steps="58"/></proof>
  <proof prover="1" steplimit="6115"><result status="valid" steps="5559"/></proof>
  <proof prover="2" obsolete="true"><result status="valid" steps="9337"/></proof>
  </goal>
  <goal name="def&#39;vc.17" proved="true">
  <proof prover="0" timelimit="1" memlimit="1000" obsolete="true"><result status="highfailure"/></proof>
  <proof prover="1" steplimit="7736"><result status="valid" steps="7032"/></proof>
  <proof prover="2" obsolete="true"><result status="highfailure"/></proof>
  </goal>
  <goal name="def&#39;vc.18" proved="true">
  <proof prover="0" steplimit="353" obsolete="true"><result status="steplimitexceeded" steps="325"/></proof>
  <proof prover="1" steplimit="7233"><result status="valid" steps="6575"/></proof>
  <proof prover="2" obsolete="true"><result status="valid" steps="28902"/></proof>
  </goal>
  <goal name="def&#39;vc.19" proved="true">
  <proof prover="0" timelimit="1" memlimit="1000" obsolete="true"><result status="failure" steps="0"/></proof>
  <proof prover="1" steplimit="7272"><result status="valid" steps="6610"/></proof>
  <proof prover="2" obsolete="true"><result status="failure" steps="0"/></proof>
  </goal>
  <goal name="def&#39;vc.20" proved="true">
  <proof prover="3"><result status="valid" steps="1"/></proof>
  </goal>
  <goal name="def&#39;vc.21" proved="true">
  <proof prover="0" steplimit="279" obsolete="true"><result status="steplimitexceeded" steps="247"/></proof>
  <proof prover="1" steplimit="8180"><result status="valid" steps="7436"/></proof>
  <proof prover="2" obsolete="true"><result status="valid" steps="31129"/></proof>
  </goal>
  <goal name="def&#39;vc.22" proved="true">
  <proof prover="0" timelimit="1" memlimit="1000" obsolete="true"><result status="failure" steps="0"/></proof>
  <proof prover="1" steplimit="9476"><result status="valid" steps="8614"/></proof>
  <proof prover="2" obsolete="true"><result status="failure" steps="0"/></proof>
  </goal>
  <goal name="def&#39;vc.23" proved="true">
  <proof prover="0" steplimit="149" obsolete="true"><result status="steplimitexceeded" steps="150"/></proof>
  <proof prover="1" steplimit="8675"><result status="valid" steps="7886"/></proof>
  <proof prover="2" obsolete="true"><result status="valid" steps="32459"/></proof>
  </goal>
  <goal name="def&#39;vc.24" proved="true">
  <proof prover="0" timelimit="1" memlimit="1000" obsolete="true"><result status="failure" steps="0"/></proof>
  <proof prover="1" steplimit="10545"><result status="valid" steps="9586"/></proof>
  <proof prover="2" obsolete="true"><result status="highfailure"/></proof>
  </goal>
  <goal name="def&#39;vc.25" proved="true">
  <proof prover="3"><result status="valid" steps="1"/></proof>
  </goal>
  <goal name="def&#39;vc.26" proved="true">
  <proof prover="0" timelimit="1" memlimit="1000" obsolete="true"><result status="highfailure"/></proof>
  <proof prover="1" steplimit="5061"><result status="valid" steps="4600"/></proof>
  <proof prover="2" obsolete="true"><result status="valid" steps="4864"/></proof>
  </goal>
  <goal name="def&#39;vc.27" proved="true">
  <proof prover="0" timelimit="1" memlimit="1000" obsolete="true"><result status="highfailure"/></proof>
  <proof prover="1" steplimit="9916"><result status="valid" steps="9014"/></proof>
  <proof prover="2" obsolete="true"><result status="valid" steps="37920"/></proof>
  </goal>
  <goal name="def&#39;vc.28" proved="true">
  <proof prover="3"><result status="valid" steps="1"/></proof>
  </goal>
  <goal name="def&#39;vc.29" proved="true">
  <proof prover="3"><result status="valid" steps="1"/></proof>
  </goal>
  <goal name="def&#39;vc.30" proved="true">
  <proof prover="0" steplimit="61" obsolete="true"><result status="steplimitexceeded" steps="62"/></proof>
  <proof prover="1" steplimit="5682"><result status="valid" steps="5165"/></proof>
  <proof prover="2" obsolete="true"><result status="valid" steps="8357"/></proof>
  </goal>
  <goal name="def&#39;vc.31" proved="true">
  <proof prover="0" steplimit="157" obsolete="true"><result status="steplimitexceeded" steps="158"/></proof>
  <proof prover="1" steplimit="10266"><result status="valid" steps="9332"/></proof>
  <proof prover="2" obsolete="true"><result status="valid" steps="35202"/></proof>
  </goal>
  <goal name="def&#39;vc.32" proved="true">
  <proof prover="0" timelimit="1" memlimit="1000" obsolete="true"><result status="failure" steps="0"/></proof>
  <proof prover="1" steplimit="12145"><result status="valid" steps="11040"/></proof>
  <proof prover="2" obsolete="true"><result status="valid" steps="40860"/></proof>
  </goal>
  <goal name="def&#39;vc.33" proved="true">
  <proof prover="3"><result status="valid" steps="1"/></proof>
  </goal>
  <goal name="def&#39;vc.34" proved="true">
  <proof prover="0" steplimit="31" obsolete="true"><result status="steplimitexceeded" steps="32"/></proof>
  <proof prover="1" steplimit="5660"><result status="valid" steps="5145"/></proof>
  <proof prover="2" obsolete="true"><result status="valid" steps="4073"/></proof>
  </goal>
  <goal name="def&#39;vc.35" proved="true">
  <proof prover="0" steplimit="200" obsolete="true"><result status="steplimitexceeded" steps="158"/></proof>
  <proof prover="1" steplimit="7500"><result status="valid" steps="6818"/></proof>
  <proof prover="2" obsolete="true"><result status="valid" steps="14895"/></proof>
  </goal>
  <goal name="def&#39;vc.36" proved="true">
  <proof prover="3"><result status="valid" steps="1"/></proof>
  </goal>
  <goal name="def&#39;vc.37" proved="true">
  <proof prover="0" steplimit="224" obsolete="true"><result status="steplimitexceeded" steps="176"/></proof>
  <proof prover="1" steplimit="8934"><result status="valid" steps="8121"/></proof>
  <proof prover="2" obsolete="true"><result status="valid" steps="43017"/></proof>
  </goal>
  <goal name="def&#39;vc.38" proved="true">
  <proof prover="0" steplimit="294" obsolete="true"><result status="steplimitexceeded" steps="222"/></proof>
  <proof prover="1" steplimit="10565"><result status="valid" steps="9604"/></proof>
  <proof prover="2" obsolete="true"><result status="valid" steps="43646"/></proof>
  </goal>
  <goal name="def&#39;vc.39" proved="true">
  <proof prover="0" steplimit="157" obsolete="true"><result status="steplimitexceeded" steps="138"/></proof>
  <proof prover="1" steplimit="9809"><result status="valid" steps="8917"/></proof>
  <proof prover="2" obsolete="true"><result status="valid" steps="44349"/></proof>
  </goal>
  <goal name="def&#39;vc.40" proved="true">
  <proof prover="0" steplimit="434" obsolete="true"><result status="steplimitexceeded" steps="351"/></proof>
  <proof prover="1" steplimit="11683"><result status="valid" steps="10620"/></proof>
  <proof prover="2" obsolete="true"><result status="valid" steps="45078"/></proof>
  </goal>
  <goal name="def&#39;vc.41" proved="true">
  <proof prover="3"><result status="valid" steps="1"/></proof>
  </goal>
  <goal name="def&#39;vc.42" proved="true">
  <proof prover="0" steplimit="359" obsolete="true"><result status="steplimitexceeded" steps="287"/></proof>
  <proof prover="1" steplimit="7387"><result status="valid" steps="6715"/></proof>
  <proof prover="2" obsolete="true"><result status="valid" steps="5818"/></proof>
  </goal>
  <goal name="def&#39;vc.43" proved="true">
  <proof prover="0" steplimit="401" obsolete="true"><result status="steplimitexceeded" steps="291"/></proof>
  <proof prover="1" steplimit="10976"><result status="valid" steps="9978"/></proof>
  <proof prover="2" obsolete="true"><result status="valid" steps="22017"/></proof>
  </goal>
  <goal name="def&#39;vc.44" proved="true">
  <proof prover="3"><result status="valid" steps="1"/></proof>
  </goal>
  <goal name="def&#39;vc.45" proved="true">
  <proof prover="3"><result status="valid" steps="1"/></proof>
  </goal>
  <goal name="def&#39;vc.46" proved="true">
  <proof prover="0" steplimit="57" obsolete="true"><result status="steplimitexceeded" steps="58"/></proof>
  <proof prover="1" steplimit="7761"><result status="valid" steps="7055"/></proof>
  <proof prover="2" obsolete="true"><result status="valid" steps="8744"/></proof>
  </goal>
  <goal name="def&#39;vc.47" proved="true">
  <proof prover="0" steplimit="70" obsolete="true"><result status="steplimitexceeded" steps="71"/></proof>
  <proof prover="1" steplimit="10508"><result status="valid" steps="9552"/></proof>
  <proof prover="2" obsolete="true"><result status="valid" steps="21277"/></proof>
  </goal>
  <goal name="def&#39;vc.48" proved="true">
  <proof prover="0" steplimit="127" obsolete="true"><result status="steplimitexceeded" steps="130"/></proof>
  <proof prover="1" steplimit="13151"><result status="valid" steps="11955"/></proof>
  <proof prover="2" obsolete="true"><result status="valid" steps="55270"/></proof>
  </goal>
  <goal name="def&#39;vc.49" proved="true">
  <proof prover="0" timelimit="1" memlimit="1000" obsolete="true"><result status="failure" steps="0"/></proof>
  <proof prover="1" steplimit="11549"><result status="valid" steps="10499"/></proof>
  <proof prover="2" obsolete="true"><result status="highfailure"/></proof>
  </goal>
  <goal name="def&#39;vc.50" proved="true">
  <proof prover="0" timelimit="1" memlimit="1000" obsolete="true"><result status="highfailure"/></proof>
  <proof prover="1" steplimit="11588"><result status="valid" steps="10534"/></proof>
  <proof prover="2" obsolete="true"><result status="highfailure"/></proof>
  </goal>
  <goal name="def&#39;vc.51" proved="true">
  <proof prover="3"><result status="valid" steps="1"/></proof>
  </goal>
  <goal name="def&#39;vc.52" proved="true">
  <proof prover="0" steplimit="417" obsolete="true"><result status="steplimitexceeded" steps="322"/></proof>
  <proof prover="1" steplimit="12497"><result status="valid" steps="11360"/></proof>
  <proof prover="2" obsolete="true"><result status="valid" steps="55371"/></proof>
  </goal>
  <goal name="def&#39;vc.53" proved="true">
  <proof prover="0" steplimit="529" obsolete="true"><result status="steplimitexceeded" steps="408"/></proof>
  <proof prover="1" steplimit="14741"><result status="valid" steps="13400"/></proof>
  <proof prover="2" obsolete="true"><result status="highfailure"/></proof>
  </goal>
  <goal name="def&#39;vc.54" proved="true">
  <proof prover="0" steplimit="206" obsolete="true"><result status="steplimitexceeded" steps="167"/></proof>
  <proof prover="1" steplimit="12992"><result status="valid" steps="11810"/></proof>
  <proof prover="2" obsolete="true"><result status="valid" steps="56701"/></proof>
  </goal>
  <goal name="def&#39;vc.55" proved="true">
  <proof prover="0" timelimit="1" memlimit="1000" obsolete="true"><result status="failure" steps="0"/></proof>
  <proof prover="1" steplimit="15826"><result status="valid" steps="14387"/></proof>
  <proof prover="2" obsolete="true"><result status="highfailure"/></proof>
  </goal>
  <goal name="def&#39;vc.56" proved="true">
  <proof prover="3"><result status="valid" steps="1"/></proof>
  </goal>
  <goal name="def&#39;vc.57" proved="true">
  <proof prover="0" timelimit="1" memlimit="1000" obsolete="true"><result status="highfailure"/></proof>
  <proof prover="1" steplimit="8351"><result status="valid" steps="7591"/></proof>
  <proof prover="2" obsolete="true"><result status="valid" steps="7217"/></proof>
  </goal>
  <goal name="def&#39;vc.58" proved="true">
  <proof prover="0" timelimit="1" memlimit="1000" obsolete="true"><result status="failure" steps="0"/></proof>
  <proof prover="1" steplimit="14342"><result status="valid" steps="13038"/></proof>
  <proof prover="2" obsolete="true"><result status="failure" steps="0"/></proof>
  </goal>
  <goal name="def&#39;vc.59" proved="true">
  <proof prover="3"><result status="valid" steps="1"/></proof>
  </goal>
  <goal name="def&#39;vc.60" proved="true">
  <proof prover="3"><result status="valid" steps="1"/></proof>
  </goal>
  <goal name="def&#39;vc.61" proved="true">
  <proof prover="0" steplimit="74" obsolete="true"><result status="steplimitexceeded" steps="75"/></proof>
  <proof prover="1" steplimit="8970"><result status="valid" steps="8154"/></proof>
  <proof prover="2" obsolete="true"><result status="valid" steps="12594"/></proof>
  </goal>
  <goal name="def&#39;vc.62" proved="true">
  <proof prover="0" steplimit="216" obsolete="true"><result status="steplimitexceeded" steps="178"/></proof>
  <proof prover="1" steplimit="15640"><result status="valid" steps="14218"/></proof>
  <proof prover="2" obsolete="true"><result status="valid" steps="62893"/></proof>
  </goal>
  <goal name="def&#39;vc.63" proved="true">
  <proof prover="0" timelimit="1" memlimit="1000" obsolete="true"><result status="highfailure"/></proof>
  <proof prover="1" steplimit="17981"><result status="valid" steps="16346"/></proof>
  <proof prover="2" obsolete="true"><result status="valid" steps="67263"/></proof>
  </goal>
  <goal name="def&#39;vc.64" proved="true">
  <proof prover="0" steplimit="46" obsolete="true"><result status="steplimitexceeded" steps="47"/></proof>
  <proof prover="1" steplimit="1928"><result status="valid" steps="1752"/></proof>
  <proof prover="2" obsolete="true"><result status="valid" steps="12720"/></proof>
  </goal>
  <goal name="def&#39;vc.65" proved="true">
  <proof prover="0" steplimit="73" obsolete="true"><result status="steplimitexceeded" steps="74"/></proof>
  <proof prover="1" steplimit="2247"><result status="valid" steps="2042"/></proof>
  <proof prover="2" obsolete="true"><result status="valid" steps="13116"/></proof>
  </goal>
  <goal name="def&#39;vc.66" proved="true">
  <proof prover="0" steplimit="80" obsolete="true"><result status="steplimitexceeded" steps="82"/></proof>
  <proof prover="1" steplimit="3783"><result status="valid" steps="3439"/></proof>
  <proof prover="2" obsolete="true"><result status="valid" steps="17006"/></proof>
  </goal>
  <goal name="def&#39;vc.67" proved="true">
  <proof prover="0" steplimit="197" obsolete="true"><result status="steplimitexceeded" steps="135"/></proof>
  <proof prover="1" steplimit="4381"><result status="valid" steps="3982"/></proof>
  <proof prover="2" obsolete="true"><result status="valid" steps="17419"/></proof>
  </goal>
  <goal name="def&#39;vc.68" proved="true">
  <proof prover="3"><result status="valid" steps="1"/></proof>
  </goal>
  <goal name="def&#39;vc.69" proved="true">
  <proof prover="3"><result status="valid" steps="1"/></proof>
  </goal>
  <goal name="def&#39;vc.70" proved="true">
  <proof prover="3"><result status="valid" steps="1"/></proof>
  </goal>
  <goal name="def&#39;vc.71" proved="true">
  <proof prover="0" steplimit="1149"><result status="valid" steps="1044"/></proof>
  <proof prover="1" timelimit="1" memlimit="1000" obsolete="true"><result status="valid" steps="12684"/></proof>
  <proof prover="2" obsolete="true"><result status="valid" steps="73935"/></proof>
  </goal>
  <goal name="def&#39;vc.72" proved="true">
  <proof prover="0" steplimit="56" obsolete="true"><result status="steplimitexceeded" steps="57"/></proof>
  <proof prover="1" steplimit="12322"><result status="valid" steps="11201"/></proof>
  <proof prover="2" obsolete="true"><result status="valid" steps="14580"/></proof>
  </goal>
  <goal name="def&#39;vc.73" proved="true">
  <proof prover="0" timelimit="1" memlimit="1000" obsolete="true"><result status="highfailure"/></proof>
  <proof prover="1" timelimit="1" memlimit="1000" obsolete="true"><result status="highfailure"/></proof>
  <proof prover="2" timelimit="0" steplimit="77911" memlimit="0"><result status="valid" steps="70828"/></proof>
  </goal>
  <goal name="def&#39;vc.74" proved="true">
  <proof prover="0" timelimit="1" memlimit="1000" obsolete="true"><result status="highfailure"/></proof>
  <proof prover="1" steplimit="15386"><result status="valid" steps="13987"/></proof>
  <proof prover="2" obsolete="true"><result status="highfailure"/></proof>
  </goal>
  <goal name="def&#39;vc.75" proved="true">
  <proof prover="3"><result status="valid" steps="1"/></proof>
  </goal>
  <goal name="def&#39;vc.76" proved="true">
  <proof prover="0" timelimit="1" memlimit="1000" obsolete="true"><result status="highfailure"/></proof>
  <proof prover="1" steplimit="17657"><result status="valid" steps="16051"/></proof>
  <proof prover="2" obsolete="true"><result status="highfailure"/></proof>
  </goal>
 </transf>
 </goal>
</theory>
</file>
</why3session>
