<?xml version="1.0" encoding="UTF-8"?>
<!DOCTYPE why3session PUBLIC "-//Why3//proof session v5//EN"
"http://why3.lri.fr/why3session.dtd">
<why3session shape_version="6">
<prover id="0" name="altergo" version="1.30-gnatprove" timelimit="0" steplimit="0" memlimit="0"/>
<prover id="1" name="CVC5" version="0.0.7-gnatprove" timelimit="0" steplimit="8719" memlimit="0"/>
<prover id="2" name="Z3" version="4.5.1-gnatprove" timelimit="1" steplimit="0" memlimit="1000"/>
<prover id="3" name="Trivial" version="1.0" alternative="trivial" timelimit="1" steplimit="1" memlimit="1000"/>
<file format="gnat-json" proved="true">
<path name=".."/><path name=".."/><path name=".."/><path name=".."/><path name=".."/>
<path name=".."/><path name=".."/><path name=".."/><path name=".."/><path name=".."/>
<path name="tmp"/><path name="tmpux6py1be"/><path name="route_aggregator"/>
<path name="gnatprove"/><path name="route_aggregator__uar_maps__map.gnat-json"/>
<theory name="Route_aggregator__uar_maps__map__default_checks" proved="true">
 <goal name="def&#39;vc" proved="true">
 <transf name="split_goal_wp_conj" proved="true" >
  <goal name="def&#39;vc.0" proved="true">
  <proof prover="3"><result status="valid" steps="1"/></proof>
  </goal>
  <goal name="def&#39;vc.1" proved="true">
  <proof prover="3"><result status="valid" steps="1"/></proof>
  </goal>
  <goal name="def&#39;vc.2" proved="true">
  <proof prover="3"><result status="valid" steps="1"/></proof>
  </goal>
  <goal name="def&#39;vc.3" proved="true">
  <proof prover="3"><result status="valid" steps="1"/></proof>
  </goal>
  <goal name="def&#39;vc.4" proved="true">
  <proof prover="3"><result status="valid" steps="1"/></proof>
  </goal>
  <goal name="def&#39;vc.5" proved="true">
  <proof prover="3"><result status="valid" steps="1"/></proof>
  </goal>
  <goal name="def&#39;vc.6" proved="true">
  <proof prover="0" steplimit="273" obsolete="true"><result status="steplimitexceeded" steps="171"/></proof>
  <proof prover="1" steplimit="5204"><result status="valid" steps="4730"/></proof>
  <proof prover="2" obsolete="true"><result status="valid" steps="2470"/></proof>
  </goal>
  <goal name="def&#39;vc.7" proved="true">
  <proof prover="3"><result status="valid" steps="1"/></proof>
  </goal>
  <goal name="def&#39;vc.8" proved="true">
  <proof prover="0" steplimit="269" obsolete="true"><result status="steplimitexceeded" steps="171"/></proof>
  <proof prover="1" steplimit="4663"><result status="valid" steps="4239"/></proof>
  <proof prover="2" obsolete="true"><result status="valid" steps="2414"/></proof>
  </goal>
  <goal name="def&#39;vc.9" proved="true">
  <proof prover="3"><result status="valid" steps="1"/></proof>
  </goal>
  <goal name="def&#39;vc.10" proved="true">
  <proof prover="3"><result status="valid" steps="1"/></proof>
  </goal>
  <goal name="def&#39;vc.11" proved="true">
  <proof prover="3"><result status="valid" steps="1"/></proof>
  </goal>
  <goal name="def&#39;vc.12" proved="true">
  <proof prover="3"><result status="valid" steps="1"/></proof>
  </goal>
  <goal name="def&#39;vc.13" proved="true">
  <proof prover="3"><result status="valid" steps="1"/></proof>
  </goal>
  <goal name="def&#39;vc.14" proved="true">
  <proof prover="0" steplimit="552" obsolete="true"><result status="steplimitexceeded" steps="187"/></proof>
  <proof prover="1" steplimit="11309"><result status="valid" steps="10280"/></proof>
  <proof prover="2" obsolete="true"><result status="valid" steps="27546"/></proof>
  </goal>
  <goal name="def&#39;vc.15" proved="true">
  <proof prover="0" steplimit="938" obsolete="true"><result status="steplimitexceeded" steps="210"/></proof>
  <proof prover="1" steplimit="11818"><result status="valid" steps="10743"/></proof>
  <proof prover="2" obsolete="true"><result status="valid" steps="28070"/></proof>
  </goal>
  <goal name="def&#39;vc.16" proved="true">
  <proof prover="3"><result status="valid" steps="1"/></proof>
  </goal>
  <goal name="def&#39;vc.17" proved="true">
  <proof prover="0" steplimit="595" obsolete="true"><result status="steplimitexceeded" steps="190"/></proof>
  <proof prover="1" steplimit="9281"><result status="valid" steps="8437"/></proof>
  <proof prover="2" obsolete="true"><result status="valid" steps="26291"/></proof>
  </goal>
  <goal name="def&#39;vc.18" proved="true">
  <proof prover="0" steplimit="459" obsolete="true"><result status="steplimitexceeded" steps="182"/></proof>
  <proof prover="1" steplimit="5540"><result status="valid" steps="5036"/></proof>
  <proof prover="2" obsolete="true"><result status="valid" steps="2726"/></proof>
  </goal>
  <goal name="def&#39;vc.19" proved="true">
  <proof prover="0" steplimit="584" obsolete="true"><result status="steplimitexceeded" steps="189"/></proof>
  <proof prover="1" steplimit="14380"><result status="valid" steps="13072"/></proof>
  <proof prover="2" obsolete="true"><result status="valid" steps="48508"/></proof>
  </goal>
  <goal name="def&#39;vc.20" proved="true">
  <proof prover="0" steplimit="489" obsolete="true"><result status="steplimitexceeded" steps="184"/></proof>
  <proof prover="1" steplimit="8577"><result status="valid" steps="7797"/></proof>
  <proof prover="2" obsolete="true"><result status="valid" steps="4565"/></proof>
  </goal>
  <goal name="def&#39;vc.21" proved="true">
  <proof prover="0" timelimit="1" memlimit="1000" obsolete="true"><result status="highfailure"/></proof>
  <proof prover="1" steplimit="17307"><result status="valid" steps="15733"/></proof>
  <proof prover="2" obsolete="true"><result status="valid" steps="47921"/></proof>
  </goal>
  <goal name="def&#39;vc.22" proved="true">
  <proof prover="0" timelimit="1" memlimit="1000" obsolete="true"><result status="timeout"/></proof>
  <proof prover="1" steplimit="18872"><result status="valid" steps="17156"/></proof>
  <proof prover="2" obsolete="true"><result status="valid" steps="48431"/></proof>
  </goal>
  <goal name="def&#39;vc.23" proved="true">
  <proof prover="0" steplimit="497" obsolete="true"><result status="steplimitexceeded" steps="184"/></proof>
  <proof prover="1"><result status="valid" steps="7926"/></proof>
  <proof prover="2" obsolete="true"><result status="valid" steps="4664"/></proof>
  </goal>
  <goal name="def&#39;vc.24" proved="true">
  <proof prover="0" steplimit="857" obsolete="true"><result status="steplimitexceeded" steps="205"/></proof>
  <proof prover="1" steplimit="20528"><result status="valid" steps="18661"/></proof>
  <proof prover="2" obsolete="true"><result status="valid" steps="50462"/></proof>
  </goal>
  <goal name="def&#39;vc.25" proved="true">
  <proof prover="3"><result status="valid" steps="1"/></proof>
  </goal>
  <goal name="def&#39;vc.26" proved="true">
  <proof prover="3"><result status="valid" steps="1"/></proof>
  </goal>
  <goal name="def&#39;vc.27" proved="true">
  <proof prover="3"><result status="valid" steps="1"/></proof>
  </goal>
 </transf>
 </goal>
</theory>
</file>
</why3session>
